itk_elastix-0.23.0.dist-info/RECORD
itk_elastix-0.23.0.dist-info/WHEEL
itk_elastix-0.23.0.dist-info/METADATA
itk_elastix-0.23.0.dist-info/licenses/LICENSE
itk/itkTransformixFilterPython.py
itk/_ElastixPython.so
itk/elxParameterObjectPython.py
itk/ElastixPython.py
itk/itkElastixRegistrationMethodPython.py
itk/Configuration/ElastixConfig.py
itk/Configuration/Elastix_snake_case.py
itk_elastix.libs/libtbb-f489fd38.so.12.9
