Metadata-Version: 2.1
Name: itk-elastix
Version: 0.23.0
Summary: Provides an ITK Python interface to elastix, a toolbox for rigid and nonrigid registration of images
Keywords: itk,elastix,registration
Author: Tom Birdsong
Author-Email: "Matthew M. McCormick" <matt.mccormick@kitware.com>, ViktorvdValk <viktorvandervalk@gmail.com>, Niels Dekker <N.Dekker@lumc.nl>, Konstantinos Ntatsis <konstantinos.ntatsis323@gmail.com>
License:                                  Apache License
Classifier: Development Status :: 4 - Beta
Classifier: Intended Audience :: Developers
Classifier: Intended Audience :: Education
Classifier: Intended Audience :: Healthcare Industry
Classifier: Intended Audience :: Science/Research
Classifier: License :: OSI Approved :: Apache Software License
Classifier: Operating System :: Android
Classifier: Operating System :: MacOS
Classifier: Operating System :: Microsoft :: Windows
Classifier: Operating System :: POSIX
Classifier: Operating System :: Unix
Classifier: Programming Language :: C++
Classifier: Programming Language :: Python
Classifier: Topic :: Scientific/Engineering
Classifier: Topic :: Scientific/Engineering :: Information Analysis
Classifier: Topic :: Scientific/Engineering :: Medical Science Apps.
Classifier: Topic :: Software Development :: Libraries
Project-URL: Download, https://github.com/InsightSoftwareConsortium/ITKElastix
Project-URL: Homepage, https://github.com/InsightSoftwareConsortium/ITKElastix
Requires-Python: >=3.9
Requires-Dist: itk~=5.4.3
